gedit/__init__.py
gedit/some.py
gedit-0.0.2.dist-info/DESCRIPTION.rst
gedit-0.0.2.dist-info/METADATA
gedit-0.0.2.dist-info/RECORD
gedit-0.0.2.dist-info/WHEEL
gedit-0.0.2.dist-info/metadata.json
gedit-0.0.2.dist-info/top_level.txt
