Metadata-Version: 1.0
Name: gedit
Version: 0.0.2
Summary: Tools for geographical data processing
Home-page: https://github.com/colyk/gedit
Author: colykxer
Author-email: colykxer@gmail.com
License: MIT
Platform: UNKNOWN
